rdflib_sparql_dataframe.py
rdflib_sparql_dataframe-1.0.2.dist-info/LICENSE
rdflib_sparql_dataframe-1.0.2.dist-info/METADATA
rdflib_sparql_dataframe-1.0.2.dist-info/WHEEL
rdflib_sparql_dataframe-1.0.2.dist-info/RECORD
